kadaptest6/__init__.py
kadaptest6/data.py
kadaptest6/linked/__init__.py
kadaptest6/linked/bicycle.py
kadaptest6/linked/child.py
kadaptest6/linked/city.py
kadaptest6/linked/freezing.py
kadaptest6/linked/holiday.py
kadaptest6/linked/jaywalking.py
kadaptest6/linked/local.py
kadaptest6/linked/motorcycle.py
kadaptest6/linked/oldman.py
kadaptest6/linked/schoolzone.py
kadaptest6/linked/violation.py
kadaptest6/retained/__init__.py
kadaptest6/retained/retained.py
kadaptest6/retained/files/__init__.py
kadaptest6/vin_decoder/__init__.py
kadaptest6/vin_decoder/decoder.py
kadaptest6-0.0.1.dist-info/LICENSE
kadaptest6-0.0.1.dist-info/METADATA
kadaptest6-0.0.1.dist-info/WHEEL
kadaptest6-0.0.1.dist-info/top_level.txt
kadaptest6-0.0.1.dist-info/RECORD
