Metadata-Version: 2.1
Name: kadaptest6
Version: 0.0.1
Summary: This is kadap test package
Home-page: UNKNOWN
Author: __author__
Author-email: jklee2@katech.re.kr
License: MIT
Platform: UNKNOWN
Classifier: Programming Language :: Python :: 3
Classifier: License :: OSI Approved :: MIT License
Classifier: Operating System :: OS Independent
